[
  {
    "userId": 1,
    "id": 1,
    "image" : "donut_red1.png",
    "title": "Tasty Donut",
    "body": "Spice tasty donut family.",
    "price": "10$",
    "button": "plus_button.png"
  },
  {
    "userId": 1,
    "id": 2,
    "image" : "donut_yellow1.png",
    "title": "Pink Donut",
    "body": "Spice tasty donut family.",
    "price": "20$",
    "button": "plus_button.png"
  },
  {
    "userId": 1,
    "id": 3,
    "image" : "tasty_donut1.png",
    "title": "Floating Donut",
    "body": "Spice tasty donut family.",
    "price": "30$",
    "button": "plus_button.png"
  },
  {
    "userId": 1,
    "id": 4,
    "image" : "green_donut1.png",
    "title": "Floating Donut",
    "body": "Spice tasty donut family.",
    "price": "40$",
    "button": "plus_button.png"
  }
]